ark/__init__.py
ark/config.py
ark/decrypt.py
ark_sdk-1.0.5.dist-info/METADATA
ark_sdk-1.0.5.dist-info/WHEEL
ark_sdk-1.0.5.dist-info/top_level.txt
ark_sdk-1.0.5.dist-info/RECORD
